netwatch/__init__.py
netwatch/cli.py
netwatch/monitor.py
netwatch/web.py
netwatch/static/css/style.css
netwatch/static/js/app.js
netwatch/templates/index.html
netwatch_monitor-1.1.2.dist-info/licenses/LICENSE
netwatch_monitor-1.1.2.dist-info/METADATA
netwatch_monitor-1.1.2.dist-info/WHEEL
netwatch_monitor-1.1.2.dist-info/entry_points.txt
netwatch_monitor-1.1.2.dist-info/top_level.txt
netwatch_monitor-1.1.2.dist-info/RECORD
