Metadata-Version: 2.4
Name: netwatch-monitor
Version: 1.1.2
Summary: A beautiful network monitoring tool with console and web interface
Home-page: https://github.com/PC0staS/netwatch
Author: PC0staS
Author-email: PC0staS <your-email@example.com>
License-Expression: MIT
Project-URL: Homepage, https://github.com/PC0staS/netwatch
Project-URL: Bug Reports, https://github.com/PC0staS/netwatch/issues
Project-URL: Source Code, https://github.com/PC0staS/netwatch
Project-URL: Documentation, https://github.com/PC0staS/netwatch#readme
Keywords: network monitoring,bandwidth monitor,console,ascii graphs,system monitoring,web interface
Classifier: Development Status :: 5 - Production/Stable
Classifier: Intended Audience :: System Administrators
Classifier: Intended Audience :: Developers
Classifier: Operating System :: OS Independent
Classifier: Programming Language :: Python :: 3
Classifier: Programming Language :: Python :: 3.6
Classifier: Programming Language :: Python :: 3.7
Classifier: Programming Language :: Python :: 3.8
Classifier: Programming Language :: Python :: 3.9
Classifier: Programming Language :: Python :: 3.10
Classifier: Programming Language :: Python :: 3.11
Classifier: Programming Language :: Python :: 3.12
Classifier: Topic :: System :: Monitoring
Classifier: Topic :: System :: Networking :: Monitoring
Classifier: Topic :: Utilities
Requires-Python: >=3.7
License-File: LICENSE
Requires-Dist: psutil>=5.7.0
Requires-Dist: flask>=2.3.0
Requires-Dist: flask-socketio>=5.3.0
Dynamic: author
Dynamic: home-page
Dynamic: license-file
Dynamic: requires-python
